galore_torch/__init__.py
galore_torch/adafactor.py
galore_torch/adamw.py
galore_torch/adamw8bit.py
galore_torch/galore_projector.py
galore_torch-1.0.dist-info/LICENSE
galore_torch-1.0.dist-info/METADATA
galore_torch-1.0.dist-info/WHEEL
galore_torch-1.0.dist-info/top_level.txt
galore_torch-1.0.dist-info/RECORD
