Metadata-Version: 2.1
Name: galore-torch
Version: 1.0
Summary: GaLore: Memory-Efficient LLM Training by Gradient Low-Rank Projection
Home-page: https://github.com/jiaweizzhao/GaLore
Author: Jiawei Zhao
Author-email: jiawei@caltech.edu
License: Apache 2.0
License-File: LICENSE
